{
  "buildDate": "2025-07-01T02:17:57.496Z",
  "nodeVersion": "v18.12.1",
  "platform": "win32",
  "arch": "x64",
  "commitHash": "7ab710ae0986df4f5573524362db66b59d449b00",
  "commitHashShort": "7ab710a",
  "branch": "main",
  "commitDate": "2025-07-01T02:17:25.000Z",
  "commitMessage": "Fix QR code interface desktop overflow and auto-scroll issues",
  "isDirty": true,
  "repoUrl": "https://github.com/lilzenon/kutt.git",
  "githubUrl": "https://github.com/lilzenon/kutt",
  "commitUrl": "https://github.com/lilzenon/kutt/commit/7ab710ae0986df4f5573524362db66b59d449b00",
  "displayText": "main@7ab710a*",
  "environment": "development"
}