{
  "buildDate": "2025-12-17T03:55:34.964Z",
  "nodeVersion": "v24.4.1",
  "platform": "win32",
  "arch": "x64",
  "commitHash": "f48fefda70276ba3e68eda80c0a551512e0f3e18",
  "commitHashShort": "f48fefd",
  "branch": "main",
  "commitDate": "2025-12-16T14:27:40.000Z",
  "commitMessage": "Fix Instagram in-app browser white page issue - Added SSR content injection for in-app browsers and noscript fallback",
  "isDirty": true,
  "repoUrl": "https://github.com/lilzenon/kutt.git",
  "githubUrl": "https://github.com/lilzenon/kutt",
  "commitUrl": "https://github.com/lilzenon/kutt/commit/f48fefda70276ba3e68eda80c0a551512e0f3e18",
  "displayText": "main@f48fefd*",
  "environment": "development"
}